fstelemetry/__init__.py
fstelemetry/__main__.py
fstelemetry/telemetry.py
fstelemetry-0.1.1.dist-info/LICENSE
fstelemetry-0.1.1.dist-info/METADATA
fstelemetry-0.1.1.dist-info/WHEEL
fstelemetry-0.1.1.dist-info/entry_points.txt
fstelemetry-0.1.1.dist-info/top_level.txt
fstelemetry-0.1.1.dist-info/RECORD
