Metadata-Version: 2.1
Name: fstelemetry
Version: 0.1.1
Summary: Capture FS2020 telemery to a csv file
Home-page: https://github.com/jbencina/fstelemetry
Author: John Bencina
License: MIT
Download-URL: https://github.com/jbencina/fstelemetry/archive/v0.1.1.tar.gz
Keywords: flight,simulator,simconnect,flightsim
Platform: UNKNOWN
Classifier: Development Status :: 4 - Beta
Classifier: Intended Audience :: Developers
Classifier: Topic :: Software Development
Classifier: License :: OSI Approved :: MIT License
Classifier: Operating System :: OS Independent
Classifier: Programming Language :: Python :: 3
Classifier: Programming Language :: Python :: 3.4
Classifier: Programming Language :: Python :: 3.5
Classifier: Programming Language :: Python :: 3.6
Classifier: Programming Language :: Python :: 3.7
Classifier: Programming Language :: Python :: 3.8
Classifier: Programming Language :: Python :: 3.9
Requires-Python: >=3.5
Requires-Dist: SimConnect (==0.4.23)
Requires-Dist: pyyaml
